eng_task/__init__.py
eng_task/additional_reports.py
eng_task/configwrite.py
eng_task/csv_utils.py
eng_task/main.py
eng_task/preprocess.py
eng_task-0.2.2.data/data/config/configure.ini
eng_task-0.2.2.dist-info/LICENSE
eng_task-0.2.2.dist-info/METADATA
eng_task-0.2.2.dist-info/WHEEL
eng_task-0.2.2.dist-info/top_level.txt
eng_task-0.2.2.dist-info/RECORD
